{
   "pistol": {
      "ingredients": {
         "copper-plate": 5,
         "iron-plate": 5
      },
      "time": 5,
      "results": {
         "pistol": 1
      }
   },
   "night-vision-equipment": {
      "ingredients": {
         "advanced-circuit": 5,
         "steel-plate": 10
      },
      "time": 10,
      "results": {
         "night-vision-equipment": 1
      }
   },
   "belt-immunity-equipment": {
      "ingredients": {
         "advanced-circuit": 5,
         "steel-plate": 10
      },
      "time": 10,
      "results": {
         "belt-immunity-equipment": 1
      }
   },
   "energy-shield-equipment": {
      "ingredients": {
         "advanced-circuit": 5,
         "steel-plate": 10
      },
      "time": 10,
      "results": {
         "energy-shield-equipment": 1
      }
   },
   "energy-shield-mk2-equipment": {
      "ingredients": {
         "energy-shield-equipment": 10,
         "processing-unit": 5,
         "low-density-structure": 5
      },
      "time": 10,
      "results": {
         "energy-shield-mk2-equipment": 1
      }
   },
   "battery-equipment": {
      "ingredients": {
         "battery": 5,
         "steel-plate": 10
      },
      "time": 10,
      "results": {
         "battery-equipment": 1
      }
   },
   "battery-mk2-equipment": {
      "ingredients": {
         "battery-equipment": 10,
         "processing-unit": 15,
         "low-density-structure": 5
      },
      "time": 10,
      "results": {
         "battery-mk2-equipment": 1
      }
   },
   "solar-panel-equipment": {
      "ingredients": {
         "solar-panel": 1,
         "advanced-circuit": 2,
         "steel-plate": 5
      },
      "time": 10,
      "results": {
         "solar-panel-equipment": 1
      }
   },
   "personal-laser-defense-equipment": {
      "ingredients": {
         "processing-unit": 20,
         "low-density-structure": 5,
         "laser-turret": 5
      },
      "time": 10,
      "results": {
         "personal-laser-defense-equipment": 1
      }
   },
   "discharge-defense-equipment": {
      "ingredients": {
         "processing-unit": 5,
         "steel-plate": 20,
         "laser-turret": 10
      },
      "time": 10,
      "results": {
         "discharge-defense-equipment": 1
      }
   },
   "discharge-defense-remote": {
      "ingredients": {
         "electronic-circuit": 1
      },
      "time": 0.5,
      "results": {
         "discharge-defense-remote": 1
      }
   },
   "personal-roboport-equipment": {
      "ingredients": {
         "advanced-circuit": 10,
         "iron-gear-wheel": 40,
         "steel-plate": 20,
         "battery": 45
      },
      "time": 10,
      "results": {
         "personal-roboport-equipment": 1
      }
   },
   "personal-roboport-mk2-equipment": {
      "ingredients": {
         "personal-roboport-equipment": 5,
         "processing-unit": 100,
         "low-density-structure": 20
      },
      "time": 20,
      "results": {
         "personal-roboport-mk2-equipment": 1
      }
   },
   "artillery-targeting-remote": {
      "ingredients": {
         "processing-unit": 1,
         "radar": 1
      },
      "time": 0.5,
      "results": {
         "artillery-targeting-remote": 1
      }
   },
   "submachine-gun": {
      "ingredients": {
         "iron-gear-wheel": 10,
         "copper-plate": 5,
         "iron-plate": 10
      },
      "time": 0.5,
      "results": {
         "submachine-gun": 1
      }
   },
   "flamethrower": {
      "ingredients": {
         "steel-plate": 5,
         "iron-gear-wheel": 10
      },
      "time": 10,
      "results": {
         "flamethrower": 1
      }
   },
   "light-armor": {
      "ingredients": {
         "iron-plate": 40
      },
      "time": 3,
      "results": {
         "light-armor": 1
      }
   },
   "car": {
      "ingredients": {
         "engine-unit": 8,
         "iron-plate": 20,
         "steel-plate": 5
      },
      "time": 2,
      "results": {
         "car": 1
      }
   },
   "heavy-armor": {
      "ingredients": {
         "copper-plate": 100,
         "steel-plate": 50
      },
      "time": 8,
      "results": {
         "heavy-armor": 1
      }
   },
   "tank": {
      "ingredients": {
         "engine-unit": 32,
         "steel-plate": 50,
         "iron-gear-wheel": 15,
         "advanced-circuit": 10
      },
      "time": 0.5,
      "results": {
         "tank": 1
      }
   },
   "modular-armor": {
      "ingredients": {
         "advanced-circuit": 30,
         "steel-plate": 50
      },
      "time": 15,
      "results": {
         "modular-armor": 1
      }
   },
   "power-armor": {
      "ingredients": {
         "processing-unit": 40,
         "electric-engine-unit": 20,
         "steel-plate": 40
      },
      "time": 20,
      "results": {
         "power-armor": 1
      }
   },
   "power-armor-mk2": {
      "ingredients": {
         "effectivity-module-2": 25,
         "speed-module-2": 25,
         "processing-unit": 60,
         "electric-engine-unit": 40,
         "low-density-structure": 30
      },
      "time": 25,
      "results": {
         "power-armor-mk2": 1
      }
   },
   "shotgun": {
      "ingredients": {
         "iron-plate": 15,
         "iron-gear-wheel": 5,
         "copper-plate": 10,
         "wood": 5
      },
      "time": 10,
      "results": {
         "shotgun": 1
      }
   },
   "rocket-silo": {
      "ingredients": {
         "steel-plate": 1000,
         "concrete": 1000,
         "pipe": 100,
         "processing-unit": 200,
         "electric-engine-unit": 200
      },
      "time": 30,
      "results": {
         "rocket-silo": 1
      }
   },
   "combat-shotgun": {
      "ingredients": {
         "steel-plate": 15,
         "iron-gear-wheel": 5,
         "copper-plate": 10,
         "wood": 10
      },
      "time": 10,
      "results": {
         "combat-shotgun": 1
      }
   }
}